sesd.py
sesd-0.2.dist-info/LICENSE
sesd-0.2.dist-info/METADATA
sesd-0.2.dist-info/WHEEL
sesd-0.2.dist-info/top_level.txt
sesd-0.2.dist-info/RECORD
