Metadata-Version: 2.1
Name: sesd
Version: 0.2
Summary: Anomaly detection algorithm implemented at Twitter
Home-page: https://github.com/nachonavarro/seasonal-esd-anomaly-detection
Author: Nacho Navarro
Author-email: nachonavarroasv@gmail.com
License: UNKNOWN
Platform: UNKNOWN
Classifier: Programming Language :: Python :: 2
Classifier: Programming Language :: Python :: 3
Classifier: License :: OSI Approved :: GNU General Public License v3 (GPLv3)
Classifier: Operating System :: OS Independent
Requires-Dist: numpy
Requires-Dist: scipy
Requires-Dist: statsmodels
